{
  "generated_at": "2026-04-28T15:40:49.309716+00:00",
  "trace_root": "P:\\packages\\yt-is\\.logs\\worker_count_trials",
  "cohort_json": "P:\\packages\\yt-is\\.logs\\breadth_scaling_series\\cohort.double_buffered.json",
  "source_url": "https://www.youtube.com/channel/UCYTISFALLBACKBMK",
  "policy": "notebooklm_route_plus_fallback_30s_1w",
  "limit": 400,
  "batch_size": 200,
  "reusable_pipeline_mode": "double_buffered",
  "phase_a_workers": 4,
  "phase_b_workers": [],
  "manifest_json": "P:\\packages\\yt-is\\tests\\fixtures\\shared_benchmark_manifest.json",
  "phase_a": {
    "name": "breadth",
    "tiers": [
      {
        "name": "narrow",
        "description": "Narrow cohort",
        "cohort_shape": "captioned",
        "sample_label": "breadth_narrow",
        "manifest_families": null
      }
    ],
    "runs": [
      {
        "tier": {
          "name": "narrow",
          "description": "Narrow cohort",
          "cohort_shape": "captioned",
          "sample_label": "breadth_narrow",
          "manifest_families": null
        },
        "workers": 4,
        "limit": 400,
        "batch_size": 200,
        "policy": "notebooklm_route_plus_fallback_30s_1w",
        "reusable_pipeline_mode": "double_buffered",
        "trace_root": "P:\\packages\\yt-is\\.logs\\worker_count_trials",
        "cohort_json": "P:\\packages\\yt-is\\.logs\\breadth_scaling_series\\cohort.double_buffered.narrow.json",
        "output_root": "P:\\packages\\yt-is\\.logs\\pipeline_mode_comparison_400_v2\\double_buffered\\phase_a\\narrow",
        "command": [
          "C:\\Python314\\python.exe",
          "P:\\packages\\yt-is\\bin\\csf-fallback-crossover-benchmark",
          "--trace-root",
          "P:\\packages\\yt-is\\.logs\\worker_count_trials",
          "--cohort-json",
          "P:\\packages\\yt-is\\.logs\\breadth_scaling_series\\cohort.double_buffered.narrow.json",
          "--output-root",
          "P:\\packages\\yt-is\\.logs\\pipeline_mode_comparison_400_v2\\double_buffered\\phase_a\\narrow",
          "--source-url",
          "https://www.youtube.com/channel/UCYTISFALLBACKBMK",
          "--workers",
          "4",
          "--limit",
          "400",
          "--batch-size",
          "200",
          "--policy",
          "notebooklm_route_plus_fallback_30s_1w",
          "--cohort-shape",
          "captioned",
          "--worker-state-root",
          "P:\\packages\\yt-is\\.logs\\pipeline_mode_comparison_400_v2\\double_buffered\\phase_a\\narrow\\worker_states",
          "--sample-label",
          "breadth_narrow"
        ],
        "returncode": 0,
        "benchmark_summary_path": "P:\\packages\\yt-is\\.logs\\pipeline_mode_comparison_400_v2\\double_buffered\\phase_a\\narrow\\benchmark_summary.json",
        "aggregate": {
          "row_count": 2,
          "success_count_total": 150,
          "fail_count_total": 200,
          "skip_count_total": 0,
          "processed_count_total": 350,
          "hot_path_success_count_total": 150,
          "transcript_fallback_success_count_total": 0,
          "elapsed_s_total": 1245.191,
          "process_elapsed_s_total": 1245.478,
          "add_elapsed_s_total": 371.144,
          "readiness_elapsed_s_total": 0.0,
          "cleanup_elapsed_s_total": 56.492999999999995,
          "worker_idle_wait_s_total": 817.554,
          "source_ready_age_s_total": 1913.513,
          "source_ready_age_s_max": 51.184,
          "shared_retry_deferred_count_total": 0.0,
          "shared_retry_recovered_count_total": 0.0,
          "shared_retry_final_failed_count_total": 0.0,
          "shared_retry_processed_count_total": 0.0,
          "youtube_ytdlp_elapsed_s_total": 7.992,
          "youtube_ytdlp_elapsed_s_max": 2.889,
          "youtube_ytdlp_elapsed_s_count_total": 3,
          "youtube_page_elapsed_s_total": 0.0,
          "youtube_page_elapsed_s_max": 0.0,
          "youtube_page_elapsed_s_count_total": 0,
          "content_fetch_status_counts_total": {
            "ready": 150
          },
          "videos_per_hour": 433.67,
          "hot_path_videos_per_hour": 433.67,
          "transcript_fallback_videos_per_hour": 0.0,
          "processed_per_hour": 1011.89,
          "source_ready_age_s_avg": 12.757,
          "youtube_ytdlp_elapsed_s_avg": 2.664,
          "youtube_page_elapsed_s_avg": 0.0
        },
        "row_count": 2,
        "success_count_total": 150,
        "fail_count_total": 200,
        "skip_count_total": 0,
        "processed_count_total": 350,
        "hot_path_success_count_total": 150,
        "transcript_fallback_success_count_total": 0,
        "elapsed_s_total": 1245.191,
        "process_elapsed_s_total": 1245.478,
        "add_elapsed_s_total": 371.144,
        "readiness_elapsed_s_total": 0.0,
        "cleanup_elapsed_s_total": 56.492999999999995,
        "worker_idle_wait_s_total": 817.554,
        "source_ready_age_s_total": 1913.513,
        "source_ready_age_s_max": 51.184,
        "shared_retry_deferred_count_total": 0.0,
        "shared_retry_recovered_count_total": 0.0,
        "shared_retry_final_failed_count_total": 0.0,
        "shared_retry_processed_count_total": 0.0,
        "youtube_ytdlp_elapsed_s_total": 7.992,
        "youtube_ytdlp_elapsed_s_max": 2.889,
        "youtube_ytdlp_elapsed_s_count_total": 3,
        "youtube_page_elapsed_s_total": 0.0,
        "youtube_page_elapsed_s_max": 0.0,
        "youtube_page_elapsed_s_count_total": 0,
        "content_fetch_status_counts_total": {
          "ready": 150
        },
        "videos_per_hour": 433.67,
        "hot_path_videos_per_hour": 433.67,
        "transcript_fallback_videos_per_hour": 0.0,
        "processed_per_hour": 1011.89,
        "source_ready_age_s_avg": 12.757,
        "youtube_ytdlp_elapsed_s_avg": 2.664,
        "youtube_page_elapsed_s_avg": 0.0
      }
    ],
    "winner": {
      "tier": {
        "name": "narrow",
        "description": "Narrow cohort",
        "cohort_shape": "captioned",
        "sample_label": "breadth_narrow",
        "manifest_families": null
      },
      "workers": 4,
      "limit": 400,
      "batch_size": 200,
      "policy": "notebooklm_route_plus_fallback_30s_1w",
      "reusable_pipeline_mode": "double_buffered",
      "trace_root": "P:\\packages\\yt-is\\.logs\\worker_count_trials",
      "cohort_json": "P:\\packages\\yt-is\\.logs\\breadth_scaling_series\\cohort.double_buffered.narrow.json",
      "output_root": "P:\\packages\\yt-is\\.logs\\pipeline_mode_comparison_400_v2\\double_buffered\\phase_a\\narrow",
      "command": [
        "C:\\Python314\\python.exe",
        "P:\\packages\\yt-is\\bin\\csf-fallback-crossover-benchmark",
        "--trace-root",
        "P:\\packages\\yt-is\\.logs\\worker_count_trials",
        "--cohort-json",
        "P:\\packages\\yt-is\\.logs\\breadth_scaling_series\\cohort.double_buffered.narrow.json",
        "--output-root",
        "P:\\packages\\yt-is\\.logs\\pipeline_mode_comparison_400_v2\\double_buffered\\phase_a\\narrow",
        "--source-url",
        "https://www.youtube.com/channel/UCYTISFALLBACKBMK",
        "--workers",
        "4",
        "--limit",
        "400",
        "--batch-size",
        "200",
        "--policy",
        "notebooklm_route_plus_fallback_30s_1w",
        "--cohort-shape",
        "captioned",
        "--worker-state-root",
        "P:\\packages\\yt-is\\.logs\\pipeline_mode_comparison_400_v2\\double_buffered\\phase_a\\narrow\\worker_states",
        "--sample-label",
        "breadth_narrow"
      ],
      "returncode": 0,
      "benchmark_summary_path": "P:\\packages\\yt-is\\.logs\\pipeline_mode_comparison_400_v2\\double_buffered\\phase_a\\narrow\\benchmark_summary.json",
      "aggregate": {
        "row_count": 2,
        "success_count_total": 150,
        "fail_count_total": 200,
        "skip_count_total": 0,
        "processed_count_total": 350,
        "hot_path_success_count_total": 150,
        "transcript_fallback_success_count_total": 0,
        "elapsed_s_total": 1245.191,
        "process_elapsed_s_total": 1245.478,
        "add_elapsed_s_total": 371.144,
        "readiness_elapsed_s_total": 0.0,
        "cleanup_elapsed_s_total": 56.492999999999995,
        "worker_idle_wait_s_total": 817.554,
        "source_ready_age_s_total": 1913.513,
        "source_ready_age_s_max": 51.184,
        "shared_retry_deferred_count_total": 0.0,
        "shared_retry_recovered_count_total": 0.0,
        "shared_retry_final_failed_count_total": 0.0,
        "shared_retry_processed_count_total": 0.0,
        "youtube_ytdlp_elapsed_s_total": 7.992,
        "youtube_ytdlp_elapsed_s_max": 2.889,
        "youtube_ytdlp_elapsed_s_count_total": 3,
        "youtube_page_elapsed_s_total": 0.0,
        "youtube_page_elapsed_s_max": 0.0,
        "youtube_page_elapsed_s_count_total": 0,
        "content_fetch_status_counts_total": {
          "ready": 150
        },
        "videos_per_hour": 433.67,
        "hot_path_videos_per_hour": 433.67,
        "transcript_fallback_videos_per_hour": 0.0,
        "processed_per_hour": 1011.89,
        "source_ready_age_s_avg": 12.757,
        "youtube_ytdlp_elapsed_s_avg": 2.664,
        "youtube_page_elapsed_s_avg": 0.0
      },
      "row_count": 2,
      "success_count_total": 150,
      "fail_count_total": 200,
      "skip_count_total": 0,
      "processed_count_total": 350,
      "hot_path_success_count_total": 150,
      "transcript_fallback_success_count_total": 0,
      "elapsed_s_total": 1245.191,
      "process_elapsed_s_total": 1245.478,
      "add_elapsed_s_total": 371.144,
      "readiness_elapsed_s_total": 0.0,
      "cleanup_elapsed_s_total": 56.492999999999995,
      "worker_idle_wait_s_total": 817.554,
      "source_ready_age_s_total": 1913.513,
      "source_ready_age_s_max": 51.184,
      "shared_retry_deferred_count_total": 0.0,
      "shared_retry_recovered_count_total": 0.0,
      "shared_retry_final_failed_count_total": 0.0,
      "shared_retry_processed_count_total": 0.0,
      "youtube_ytdlp_elapsed_s_total": 7.992,
      "youtube_ytdlp_elapsed_s_max": 2.889,
      "youtube_ytdlp_elapsed_s_count_total": 3,
      "youtube_page_elapsed_s_total": 0.0,
      "youtube_page_elapsed_s_max": 0.0,
      "youtube_page_elapsed_s_count_total": 0,
      "content_fetch_status_counts_total": {
        "ready": 150
      },
      "videos_per_hour": 433.67,
      "hot_path_videos_per_hour": 433.67,
      "transcript_fallback_videos_per_hour": 0.0,
      "processed_per_hour": 1011.89,
      "source_ready_age_s_avg": 12.757,
      "youtube_ytdlp_elapsed_s_avg": 2.664,
      "youtube_page_elapsed_s_avg": 0.0
    }
  },
  "phase_b": {
    "name": "scaling",
    "tier": {
      "name": "narrow",
      "description": "Narrow cohort",
      "cohort_shape": "captioned",
      "sample_label": "breadth_narrow",
      "manifest_families": null
    },
    "runs": []
  },
  "report_path": "P:\\packages\\yt-is\\.logs\\pipeline_mode_comparison_400_v2\\double_buffered\\breadth_series_summary.json"
}