{
  "report_version": 1,
  "status": "ok",
  "invalidated": false,
  "attempted_lane_count": 3,
  "successful_lane_count": 3,
  "failure_count": 0,
  "failures": [],
  "generated_at": "2026-05-06T16:37:27.125798+00:00",
  "metric_contract": "combined_hot_path_videos_per_hour_excludes_whisper",
  "trace_root": "P:\\\\\\\packages\\yt-is\\.logs\\worker_count_trials",
  "cohort_json": "P:\\\\\\\packages\\yt-is\\.logs\\sharded_lane_series\\optimal_search_3lane_3w_v5\\soak\\cohort.json",
  "source_url": "https://www.youtube.com/channel/UCYTISFALLBACKBMK",
  "policy": "notebooklm_route_plus_fallback_30s_1w",
  "limit": 400,
  "batch_size": 200,
  "reusable_pipeline_mode": "serial",
  "lanes": [
    {
      "lane": "a_hominidae_pro",
      "account_class": "pro",
      "workers": 4,
      "notebooklm_profile_prefix": "ytis-pro-worker",
      "browser_profile_root": "P:\\\\\\\.data\\yt-is\\browser\\notebooklm-pro",
      "worker_state_root": "P:\\\\\\\packages\\yt-is\\.logs\\sharded_lane_series\\a_hominidae_pro\\worker_states",
      "notebook_prefix": "benchmark-shard-a-hominidae-pro",
      "notebooklm_profiles": [
        "ytis-pro-worker-01",
        "ytis-pro-worker-02",
        "ytis-pro-worker-03",
        "ytis-pro-worker-04"
      ],
      "expected_email": "",
      "browser_profile_directory": "Profile",
      "coordinator_notebooklm_profile": null,
      "startup_delay_s": 0.0
    },
    {
      "lane": "troup_hominidae_free",
      "account_class": "free",
      "workers": 4,
      "notebooklm_profile_prefix": "ytis-free1-worker",
      "browser_profile_root": "P:\\\\\\\.data\\yt-is\\browser\\notebooklm-free",
      "worker_state_root": "P:\\\\\\\packages\\yt-is\\.logs\\sharded_lane_series\\troup_hominidae_free\\worker_states",
      "notebook_prefix": "benchmark-shard-troup-hominidae-free",
      "notebooklm_profiles": [
        "ytis-free1-worker-01",
        "ytis-free1-worker-02",
        "ytis-free1-worker-03",
        "ytis-free1-worker-04"
      ],
      "expected_email": "",
      "browser_profile_directory": "Default",
      "coordinator_notebooklm_profile": null,
      "startup_delay_s": 0.0
    },
    {
      "lane": "brsthomson_hotmail_free",
      "account_class": "free",
      "workers": 4,
      "notebooklm_profile_prefix": "ytis-free2-worker",
      "browser_profile_root": "P:\\\\\\\.data\\yt-is\\browser\\notebooklm-free-2",
      "worker_state_root": "P:\\\\\\\packages\\yt-is\\.logs\\sharded_lane_series\\brsthomson_hotmail_free\\worker_states",
      "notebook_prefix": "benchmark-shard-brsthomson-hotmail-free",
      "notebooklm_profiles": [
        "ytis-free2-worker-01",
        "ytis-free2-worker-02",
        "ytis-free2-worker-03",
        "ytis-free2-worker-04"
      ],
      "expected_email": "",
      "browser_profile_directory": "Default",
      "coordinator_notebooklm_profile": null,
      "startup_delay_s": 0.0
    }
  ],
  "runs": [
    {
      "status": "ok",
      "lane": "a_hominidae_pro",
      "account_class": "pro",
      "workers": 4,
      "notebooklm_profile_prefix": "ytis-pro-worker",
      "notebooklm_profiles": [
        "ytis-pro-worker-01",
        "ytis-pro-worker-02",
        "ytis-pro-worker-03",
        "ytis-pro-worker-04"
      ],
      "coordinator_notebooklm_profile": "ytis-pro-worker-01",
      "browser_profile_root": "P:\\\\\\\.data\\yt-is\\browser\\notebooklm-pro",
      "browser_profile_directory": "Profile",
      "worker_state_root": "P:\\\\\\\packages\\yt-is\\.logs\\sharded_lane_series\\a_hominidae_pro\\worker_states",
      "notebook_prefix": "benchmark-shard-a-hominidae-pro",
      "startup_delay_s": 0.0,
      "started_at": 1214225.715,
      "finished_at": 1216258.846,
      "wall_elapsed_s": 2033.131,
      "returncode": 0,
      "command": [
        "C:\\Python314\\python.exe",
        "P:\\\\\\\packages\\yt-is\\bin\\csf-fallback-crossover-benchmark",
        "--trace-root",
        "P:\\\\\\\packages\\yt-is\\.logs\\worker_count_trials",
        "--cohort-json",
        "P:\\\\\\\packages\\yt-is\\.logs\\sharded_lane_series\\optimal_search_3lane_3w_v5\\soak\\cohort.a_hominidae_pro.json",
        "--output-root",
        "P:\\\\\\\packages\\yt-is\\.logs\\sharded_lane_series\\optimal_search_3lane_3w_v5\\soak\\a_hominidae_pro",
        "--source-url",
        "https://www.youtube.com/channel/UCYTISFALLBACKBMK",
        "--workers",
        "4",
        "--limit",
        "400",
        "--batch-size",
        "200",
        "--policy",
        "notebooklm_route_plus_fallback_30s_1w",
        "--cohort-shape",
        "captioned",
        "--worker-state-root",
        "P:\\\\\\\packages\\yt-is\\.logs\\sharded_lane_series\\a_hominidae_pro\\worker_states",
        "--sample-label",
        "shard_a_hominidae_pro"
      ],
      "output_root": "P:\\\\\\\packages\\yt-is\\.logs\\sharded_lane_series\\optimal_search_3lane_3w_v5\\soak\\a_hominidae_pro",
      "stdout_path": "P:\\\\\\\packages\\yt-is\\.logs\\sharded_lane_series\\optimal_search_3lane_3w_v5\\soak\\a_hominidae_pro\\lane.stdout.txt",
      "stderr_path": "P:\\\\\\\packages\\yt-is\\.logs\\sharded_lane_series\\optimal_search_3lane_3w_v5\\soak\\a_hominidae_pro\\lane.stderr.txt",
      "lane_process_path": "P:\\\\\\\packages\\yt-is\\.logs\\sharded_lane_series\\optimal_search_3lane_3w_v5\\soak\\a_hominidae_pro\\lane_process.json",
      "benchmark_summary_path": "P:\\\\\\\packages\\yt-is\\.logs\\sharded_lane_series\\optimal_search_3lane_3w_v5\\soak\\a_hominidae_pro\\benchmark_summary.json",
      "aggregate": {
        "row_count": 2,
        "success_count_total": 396,
        "fail_count_total": 4,
        "skip_count_total": 0,
        "processed_count_total": 400,
        "hot_path_success_count_total": 396,
        "transcript_fallback_success_count_total": 0,
        "elapsed_s_total": 2031.9840000000002,
        "process_elapsed_s_total": 2032.579,
        "add_elapsed_s_total": 995.4639999999999,
        "readiness_elapsed_s_total": 0.0,
        "cleanup_elapsed_s_total": 132.845,
        "worker_idle_wait_s_total": 903.675,
        "source_ready_age_s_total": 64795.121999999996,
        "source_ready_age_s_max": 848.283,
        "shared_retry_deferred_count_total": 0.0,
        "shared_retry_recovered_count_total": 0.0,
        "shared_retry_final_failed_count_total": 0.0,
        "shared_retry_processed_count_total": 0.0,
        "youtube_ytdlp_elapsed_s_total": 395.086,
        "youtube_ytdlp_elapsed_s_max": 5.637,
        "youtube_ytdlp_elapsed_s_count_total": 159,
        "youtube_page_elapsed_s_total": 0.0,
        "youtube_page_elapsed_s_max": 0.0,
        "youtube_page_elapsed_s_count_total": 0,
        "content_fetch_status_counts_total": {
          "ready": 396,
          "command_failed": 78,
          "nlm_content_below_threshold": 1
        },
        "videos_per_hour": 701.58,
        "hot_path_videos_per_hour": 701.58,
        "transcript_fallback_videos_per_hour": 0.0,
        "processed_per_hour": 708.67,
        "source_ready_age_s_avg": 136.411,
        "youtube_ytdlp_elapsed_s_avg": 2.485,
        "youtube_page_elapsed_s_avg": 0.0
      },
      "row_count": 2,
      "success_count_total": 396,
      "fail_count_total": 4,
      "skip_count_total": 0,
      "processed_count_total": 400,
      "hot_path_success_count_total": 396,
      "transcript_fallback_success_count_total": 0,
      "elapsed_s_total": 2031.9840000000002,
      "process_elapsed_s_total": 2032.579,
      "add_elapsed_s_total": 995.4639999999999,
      "readiness_elapsed_s_total": 0.0,
      "cleanup_elapsed_s_total": 132.845,
      "worker_idle_wait_s_total": 903.675,
      "source_ready_age_s_total": 64795.121999999996,
      "source_ready_age_s_max": 848.283,
      "shared_retry_deferred_count_total": 0.0,
      "shared_retry_recovered_count_total": 0.0,
      "shared_retry_final_failed_count_total": 0.0,
      "shared_retry_processed_count_total": 0.0,
      "youtube_ytdlp_elapsed_s_total": 395.086,
      "youtube_ytdlp_elapsed_s_max": 5.637,
      "youtube_ytdlp_elapsed_s_count_total": 159,
      "youtube_page_elapsed_s_total": 0.0,
      "youtube_page_elapsed_s_max": 0.0,
      "youtube_page_elapsed_s_count_total": 0,
      "content_fetch_status_counts_total": {
        "ready": 396,
        "command_failed": 78,
        "nlm_content_below_threshold": 1
      },
      "videos_per_hour": 701.58,
      "hot_path_videos_per_hour": 701.58,
      "transcript_fallback_videos_per_hour": 0.0,
      "processed_per_hour": 708.67,
      "source_ready_age_s_avg": 136.411,
      "youtube_ytdlp_elapsed_s_avg": 2.485,
      "youtube_page_elapsed_s_avg": 0.0
    },
    {
      "status": "ok",
      "lane": "troup_hominidae_free",
      "account_class": "free",
      "workers": 4,
      "notebooklm_profile_prefix": "ytis-free1-worker",
      "notebooklm_profiles": [
        "ytis-free1-worker-01",
        "ytis-free1-worker-02",
        "ytis-free1-worker-03",
        "ytis-free1-worker-04"
      ],
      "coordinator_notebooklm_profile": "ytis-free1-worker-01",
      "browser_profile_root": "P:\\\\\\\.data\\yt-is\\browser\\notebooklm-free",
      "browser_profile_directory": "Default",
      "worker_state_root": "P:\\\\\\\packages\\yt-is\\.logs\\sharded_lane_series\\troup_hominidae_free\\worker_states",
      "notebook_prefix": "benchmark-shard-troup-hominidae-free",
      "startup_delay_s": 0.0,
      "started_at": 1214225.715,
      "finished_at": 1216737.87,
      "wall_elapsed_s": 2512.156,
      "returncode": 0,
      "command": [
        "C:\\Python314\\python.exe",
        "P:\\\\\\\packages\\yt-is\\bin\\csf-fallback-crossover-benchmark",
        "--trace-root",
        "P:\\\\\\\packages\\yt-is\\.logs\\worker_count_trials",
        "--cohort-json",
        "P:\\\\\\\packages\\yt-is\\.logs\\sharded_lane_series\\optimal_search_3lane_3w_v5\\soak\\cohort.troup_hominidae_free.json",
        "--output-root",
        "P:\\\\\\\packages\\yt-is\\.logs\\sharded_lane_series\\optimal_search_3lane_3w_v5\\soak\\troup_hominidae_free",
        "--source-url",
        "https://www.youtube.com/channel/UCYTISFALLBACKBMK",
        "--workers",
        "4",
        "--limit",
        "400",
        "--batch-size",
        "200",
        "--policy",
        "notebooklm_route_plus_fallback_30s_1w",
        "--cohort-shape",
        "captioned",
        "--worker-state-root",
        "P:\\\\\\\packages\\yt-is\\.logs\\sharded_lane_series\\troup_hominidae_free\\worker_states",
        "--sample-label",
        "shard_troup_hominidae_free"
      ],
      "output_root": "P:\\\\\\\packages\\yt-is\\.logs\\sharded_lane_series\\optimal_search_3lane_3w_v5\\soak\\troup_hominidae_free",
      "stdout_path": "P:\\\\\\\packages\\yt-is\\.logs\\sharded_lane_series\\optimal_search_3lane_3w_v5\\soak\\troup_hominidae_free\\lane.stdout.txt",
      "stderr_path": "P:\\\\\\\packages\\yt-is\\.logs\\sharded_lane_series\\optimal_search_3lane_3w_v5\\soak\\troup_hominidae_free\\lane.stderr.txt",
      "lane_process_path": "P:\\\\\\\packages\\yt-is\\.logs\\sharded_lane_series\\optimal_search_3lane_3w_v5\\soak\\troup_hominidae_free\\lane_process.json",
      "benchmark_summary_path": "P:\\\\\\\packages\\yt-is\\.logs\\sharded_lane_series\\optimal_search_3lane_3w_v5\\soak\\troup_hominidae_free\\benchmark_summary.json",
      "aggregate": {
        "row_count": 2,
        "success_count_total": 394,
        "fail_count_total": 6,
        "skip_count_total": 0,
        "processed_count_total": 400,
        "hot_path_success_count_total": 394,
        "transcript_fallback_success_count_total": 0,
        "elapsed_s_total": 2511.041,
        "process_elapsed_s_total": 2511.61,
        "add_elapsed_s_total": 1129.689,
        "readiness_elapsed_s_total": 0.0,
        "cleanup_elapsed_s_total": 80.27000000000001,
        "worker_idle_wait_s_total": 1301.0819999999999,
        "source_ready_age_s_total": 123908.491,
        "source_ready_age_s_max": 1229.821,
        "shared_retry_deferred_count_total": 0.0,
        "shared_retry_recovered_count_total": 0.0,
        "shared_retry_final_failed_count_total": 0.0,
        "shared_retry_processed_count_total": 0.0,
        "youtube_ytdlp_elapsed_s_total": 602.09,
        "youtube_ytdlp_elapsed_s_max": 5.615,
        "youtube_ytdlp_elapsed_s_count_total": 257,
        "youtube_page_elapsed_s_total": 0.0,
        "youtube_page_elapsed_s_max": 0.0,
        "youtube_page_elapsed_s_count_total": 0,
        "content_fetch_status_counts_total": {
          "ready": 394,
          "command_failed": 127,
          "nlm_content_below_threshold": 1
        },
        "videos_per_hour": 564.87,
        "hot_path_videos_per_hour": 564.87,
        "transcript_fallback_videos_per_hour": 0.0,
        "processed_per_hour": 573.47,
        "source_ready_age_s_avg": 237.373,
        "youtube_ytdlp_elapsed_s_avg": 2.343,
        "youtube_page_elapsed_s_avg": 0.0
      },
      "row_count": 2,
      "success_count_total": 394,
      "fail_count_total": 6,
      "skip_count_total": 0,
      "processed_count_total": 400,
      "hot_path_success_count_total": 394,
      "transcript_fallback_success_count_total": 0,
      "elapsed_s_total": 2511.041,
      "process_elapsed_s_total": 2511.61,
      "add_elapsed_s_total": 1129.689,
      "readiness_elapsed_s_total": 0.0,
      "cleanup_elapsed_s_total": 80.27000000000001,
      "worker_idle_wait_s_total": 1301.0819999999999,
      "source_ready_age_s_total": 123908.491,
      "source_ready_age_s_max": 1229.821,
      "shared_retry_deferred_count_total": 0.0,
      "shared_retry_recovered_count_total": 0.0,
      "shared_retry_final_failed_count_total": 0.0,
      "shared_retry_processed_count_total": 0.0,
      "youtube_ytdlp_elapsed_s_total": 602.09,
      "youtube_ytdlp_elapsed_s_max": 5.615,
      "youtube_ytdlp_elapsed_s_count_total": 257,
      "youtube_page_elapsed_s_total": 0.0,
      "youtube_page_elapsed_s_max": 0.0,
      "youtube_page_elapsed_s_count_total": 0,
      "content_fetch_status_counts_total": {
        "ready": 394,
        "command_failed": 127,
        "nlm_content_below_threshold": 1
      },
      "videos_per_hour": 564.87,
      "hot_path_videos_per_hour": 564.87,
      "transcript_fallback_videos_per_hour": 0.0,
      "processed_per_hour": 573.47,
      "source_ready_age_s_avg": 237.373,
      "youtube_ytdlp_elapsed_s_avg": 2.343,
      "youtube_page_elapsed_s_avg": 0.0
    },
    {
      "status": "ok",
      "lane": "brsthomson_hotmail_free",
      "account_class": "free",
      "workers": 4,
      "notebooklm_profile_prefix": "ytis-free2-worker",
      "notebooklm_profiles": [
        "ytis-free2-worker-01",
        "ytis-free2-worker-02",
        "ytis-free2-worker-03",
        "ytis-free2-worker-04"
      ],
      "coordinator_notebooklm_profile": "ytis-free2-worker-01",
      "browser_profile_root": "P:\\\\\\\.data\\yt-is\\browser\\notebooklm-free-2",
      "browser_profile_directory": "Default",
      "worker_state_root": "P:\\\\\\\packages\\yt-is\\.logs\\sharded_lane_series\\brsthomson_hotmail_free\\worker_states",
      "notebook_prefix": "benchmark-shard-brsthomson-hotmail-free",
      "startup_delay_s": 0.0,
      "started_at": 1214225.715,
      "finished_at": 1216637.419,
      "wall_elapsed_s": 2411.704,
      "returncode": 0,
      "command": [
        "C:\\Python314\\python.exe",
        "P:\\\\\\\packages\\yt-is\\bin\\csf-fallback-crossover-benchmark",
        "--trace-root",
        "P:\\\\\\\packages\\yt-is\\.logs\\worker_count_trials",
        "--cohort-json",
        "P:\\\\\\\packages\\yt-is\\.logs\\sharded_lane_series\\optimal_search_3lane_3w_v5\\soak\\cohort.brsthomson_hotmail_free.json",
        "--output-root",
        "P:\\\\\\\packages\\yt-is\\.logs\\sharded_lane_series\\optimal_search_3lane_3w_v5\\soak\\brsthomson_hotmail_free",
        "--source-url",
        "https://www.youtube.com/channel/UCYTISFALLBACKBMK",
        "--workers",
        "4",
        "--limit",
        "400",
        "--batch-size",
        "200",
        "--policy",
        "notebooklm_route_plus_fallback_30s_1w",
        "--cohort-shape",
        "captioned",
        "--worker-state-root",
        "P:\\\\\\\packages\\yt-is\\.logs\\sharded_lane_series\\brsthomson_hotmail_free\\worker_states",
        "--sample-label",
        "shard_brsthomson_hotmail_free"
      ],
      "output_root": "P:\\\\\\\packages\\yt-is\\.logs\\sharded_lane_series\\optimal_search_3lane_3w_v5\\soak\\brsthomson_hotmail_free",
      "stdout_path": "P:\\\\\\\packages\\yt-is\\.logs\\sharded_lane_series\\optimal_search_3lane_3w_v5\\soak\\brsthomson_hotmail_free\\lane.stdout.txt",
      "stderr_path": "P:\\\\\\\packages\\yt-is\\.logs\\sharded_lane_series\\optimal_search_3lane_3w_v5\\soak\\brsthomson_hotmail_free\\lane.stderr.txt",
      "lane_process_path": "P:\\\\\\\packages\\yt-is\\.logs\\sharded_lane_series\\optimal_search_3lane_3w_v5\\soak\\brsthomson_hotmail_free\\lane_process.json",
      "benchmark_summary_path": "P:\\\\\\\packages\\yt-is\\.logs\\sharded_lane_series\\optimal_search_3lane_3w_v5\\soak\\brsthomson_hotmail_free\\benchmark_summary.json",
      "aggregate": {
        "row_count": 2,
        "success_count_total": 395,
        "fail_count_total": 5,
        "skip_count_total": 0,
        "processed_count_total": 400,
        "hot_path_success_count_total": 395,
        "transcript_fallback_success_count_total": 0,
        "elapsed_s_total": 2410.5879999999997,
        "process_elapsed_s_total": 2411.151,
        "add_elapsed_s_total": 1216.52,
        "readiness_elapsed_s_total": 0.0,
        "cleanup_elapsed_s_total": 163.723,
        "worker_idle_wait_s_total": 1030.345,
        "source_ready_age_s_total": 81760.68000000001,
        "source_ready_age_s_max": 1192.236,
        "shared_retry_deferred_count_total": 0.0,
        "shared_retry_recovered_count_total": 0.0,
        "shared_retry_final_failed_count_total": 0.0,
        "shared_retry_processed_count_total": 0.0,
        "youtube_ytdlp_elapsed_s_total": 433.07599999999996,
        "youtube_ytdlp_elapsed_s_max": 4.867,
        "youtube_ytdlp_elapsed_s_count_total": 189,
        "youtube_page_elapsed_s_total": 0.0,
        "youtube_page_elapsed_s_max": 0.0,
        "youtube_page_elapsed_s_count_total": 0,
        "content_fetch_status_counts_total": {
          "ready": 395,
          "command_failed": 94
        },
        "videos_per_hour": 589.9,
        "hot_path_videos_per_hour": 589.9,
        "transcript_fallback_videos_per_hour": 0.0,
        "processed_per_hour": 597.36,
        "source_ready_age_s_avg": 167.2,
        "youtube_ytdlp_elapsed_s_avg": 2.291,
        "youtube_page_elapsed_s_avg": 0.0
      },
      "row_count": 2,
      "success_count_total": 395,
      "fail_count_total": 5,
      "skip_count_total": 0,
      "processed_count_total": 400,
      "hot_path_success_count_total": 395,
      "transcript_fallback_success_count_total": 0,
      "elapsed_s_total": 2410.5879999999997,
      "process_elapsed_s_total": 2411.151,
      "add_elapsed_s_total": 1216.52,
      "readiness_elapsed_s_total": 0.0,
      "cleanup_elapsed_s_total": 163.723,
      "worker_idle_wait_s_total": 1030.345,
      "source_ready_age_s_total": 81760.68000000001,
      "source_ready_age_s_max": 1192.236,
      "shared_retry_deferred_count_total": 0.0,
      "shared_retry_recovered_count_total": 0.0,
      "shared_retry_final_failed_count_total": 0.0,
      "shared_retry_processed_count_total": 0.0,
      "youtube_ytdlp_elapsed_s_total": 433.07599999999996,
      "youtube_ytdlp_elapsed_s_max": 4.867,
      "youtube_ytdlp_elapsed_s_count_total": 189,
      "youtube_page_elapsed_s_total": 0.0,
      "youtube_page_elapsed_s_max": 0.0,
      "youtube_page_elapsed_s_count_total": 0,
      "content_fetch_status_counts_total": {
        "ready": 395,
        "command_failed": 94
      },
      "videos_per_hour": 589.9,
      "hot_path_videos_per_hour": 589.9,
      "transcript_fallback_videos_per_hour": 0.0,
      "processed_per_hour": 597.36,
      "source_ready_age_s_avg": 167.2,
      "youtube_ytdlp_elapsed_s_avg": 2.291,
      "youtube_page_elapsed_s_avg": 0.0
    }
  ],
  "combined": {
    "lane_count": 3,
    "started_at": 1214225.715,
    "finished_at": 1216737.87,
    "wall_elapsed_s": 2512.155,
    "hot_path_success_count_total": 1185,
    "transcript_fallback_success_count_total": 0,
    "fail_count_total": 15,
    "processed_count_total": 1200,
    "hot_path_videos_per_hour": 1698.14,
    "transcript_fallback_videos_per_hour": 0.0,
    "processed_per_hour": 1719.64
  },
  "report_path": "P:\\\\\\\packages\\yt-is\\.logs\\sharded_lane_series\\optimal_search_3lane_3w_v5\\soak\\sharded_lane_series_summary.json"
}