{
  "started_at": "2026-04-30T00:24:29.445423+00:00",
  "finished_at": "2026-04-30T00:24:42.374100+00:00",
  "output_root": "P:\\\packages\\yt-is\\.logs\\nlm_content_probe\\residual_pro_v1\\20260430T002429Z",
  "profiles": [
    "ytis-pro-worker-02"
  ],
  "video_ids": [
    "j6lOJPRvuzc",
    "MXAvtEHyl0A"
  ],
  "notebooks": {
    "ytis-pro-worker-02": "54f25fe3-77b8-4139-b566-776a7fc12126"
  },
  "results": [
    {
      "profile": "ytis-pro-worker-02",
      "notebook_id": "54f25fe3-77b8-4139-b566-776a7fc12126",
      "video_id": "j6lOJPRvuzc",
      "source_id": "7918617c-244e-4433-a5db-766b911402b8",
      "video_duration_s": null,
      "ytdlp_classification": "ok",
      "add_result": {
        "profile": "ytis-pro-worker-02",
        "notebook_id": "54f25fe3-77b8-4139-b566-776a7fc12126",
        "video_id": "j6lOJPRvuzc",
        "url": "https://www.youtube.com/watch?v=j6lOJPRvuzc",
        "returncode": 0,
        "stdout": "Adding https://www.youtube.com/watch?v=j6lOJPRvuzc and waiting for processing...\n\u2713 Added source: Embracing Mistakes in Nutrition | Tips from a Weight Loss Expert\n(ready)\nSource ID: 7918617c-244e-4433-a5db-766b911402b8\n",
        "stderr": "",
        "elapsed_s": 2.871,
        "source_ids": [
          "7918617c-244e-4433-a5db-766b911402b8"
        ],
        "source_id": "7918617c-244e-4433-a5db-766b911402b8"
      },
      "attempts": [
        {
          "profile": "ytis-pro-worker-02",
          "source_id": "7918617c-244e-4433-a5db-766b911402b8",
          "status": "ready",
          "returncode": 0,
          "content_length": 636,
          "nlm_content_chars": 636,
          "usable_text_chars": 636,
          "stdout": "{\n  \"value\": {\n    \"content\": \"you know when you make a mistake and you're driving for example and you take a wrong turn you're not going to keep going the wrong direction right you're going to make a U-turn as immediately as you can you might even go up and over the median and turn around and get going the way that you need to well the same thing pertains to our our diet our nutrition our health if you make a mistake you know that that's okay but it's all about getting back up and moving forward in the direction that you want to go so this black or white thinking this All or Nothing mindset really gets us stuck \\n\\nand closes the doors to Future opportunities \",\n    \"title\": \"Embracing Mistakes in Nutrition | Tips from a Weight Loss Expert\",\n    \"source_type\": \"youtube\",\n    \"url\": null,\n    \"char_count\": 636\n  }\n}\n",
          "stderr": "",
          "started_at_epoch": 1777508676.076361,
          "completed_at_epoch": 1777508676.733376,
          "elapsed_s": 0.657,
          "attempt_index": 1,
          "scheduled_delay_s": 0,
          "video_id": "j6lOJPRvuzc",
          "notebook_id": "54f25fe3-77b8-4139-b566-776a7fc12126",
          "video_duration_s": null,
          "ytdlp_classification": "ok",
          "ytdlp_available": true,
          "ytdlp_availability": "public"
        }
      ]
    },
    {
      "profile": "ytis-pro-worker-02",
      "notebook_id": "54f25fe3-77b8-4139-b566-776a7fc12126",
      "video_id": "MXAvtEHyl0A",
      "source_id": "cbc62d0e-a86e-45ba-96cb-393428672102",
      "video_duration_s": null,
      "ytdlp_classification": "ok",
      "add_result": {
        "profile": "ytis-pro-worker-02",
        "notebook_id": "54f25fe3-77b8-4139-b566-776a7fc12126",
        "video_id": "MXAvtEHyl0A",
        "url": "https://www.youtube.com/watch?v=MXAvtEHyl0A",
        "returncode": 0,
        "stdout": "Adding https://www.youtube.com/watch?v=MXAvtEHyl0A and waiting for processing...\n\u2713 Added source: Understanding Belly Fat with Dr. Sean O'Mara (ready)\nSource ID: cbc62d0e-a86e-45ba-96cb-393428672102\n",
        "stderr": "",
        "elapsed_s": 3.198,
        "source_ids": [
          "cbc62d0e-a86e-45ba-96cb-393428672102"
        ],
        "source_id": "cbc62d0e-a86e-45ba-96cb-393428672102"
      },
      "attempts": [
        {
          "profile": "ytis-pro-worker-02",
          "source_id": "cbc62d0e-a86e-45ba-96cb-393428672102",
          "status": "ready",
          "returncode": 0,
          "content_length": 564,
          "nlm_content_chars": 564,
          "usable_text_chars": 564,
          "stdout": "{\n  \"value\": {\n    \"content\": \"I walk down the largest shopping mall in America which is the Mall of America in Minneapolis and I'm doing FAL fat analysis of all the people as are walking about I can't help it that's what I that's what I do I can see the effect of that visceral fat in those people's faces so contrast wise your audience can understand everybody ask how much FAL fat your have okay you want none of it it's it's secreting in how much inflammation do you want to put up with do you want something in there causing inflammation how much would you be comfortable with first \\n\\nnone \",\n    \"title\": \"Understanding Belly Fat with Dr. Sean O'Mara\",\n    \"source_type\": \"youtube\",\n    \"url\": null,\n    \"char_count\": 564\n  }\n}\n",
          "stderr": "",
          "started_at_epoch": 1777508681.5632305,
          "completed_at_epoch": 1777508682.3740425,
          "elapsed_s": 0.811,
          "attempt_index": 1,
          "scheduled_delay_s": 0,
          "video_id": "MXAvtEHyl0A",
          "notebook_id": "54f25fe3-77b8-4139-b566-776a7fc12126",
          "video_duration_s": null,
          "ytdlp_classification": "ok",
          "ytdlp_available": true,
          "ytdlp_availability": "public"
        }
      ]
    }
  ]
}